MANIFEST.in
setup.cfg
setup.py
bootsrapzz/__init__.py
bootsrapzz.egg-info/PKG-INFO
bootsrapzz.egg-info/SOURCES.txt
bootsrapzz.egg-info/dependency_links.txt
bootsrapzz.egg-info/top_level.txt
bootsrapzz/data/.DS_Store
bootsrapzz/data/readme/.DS_Store
bootsrapzz/data/readme/startbootstrap-new-age-gh-pages.zip
bootsrapzz/data/readme/startbootstrap-sb-admin-gh-pages.zip